projecc/PMa_sensitivity.py
projecc/__init__.py
projecc/projecc.py
projecc-1.1.7.dist-info/LICENSE
projecc-1.1.7.dist-info/METADATA
projecc-1.1.7.dist-info/WHEEL
projecc-1.1.7.dist-info/top_level.txt
projecc-1.1.7.dist-info/RECORD
