Metadata-Version: 2.1
Name: projecc
Version: 1.1.7
Summary: A small simple package for projecting orbital elements onto sky plane and vice versa
Home-page: https://github.com/logan-pearce/projecc
Author: Logan Pearce
Author-email: lapearce@umich.edu
License: MIT
License-File: LICENSE
Requires-Dist: numpy
Requires-Dist: astropy
